[
  {
    "id": 722,
    "name": "rowlet",
    "names": {
      "en": "rowlet",
      "de": "Bauz"
    },
    "generation_id": 7,
    "capture_rate": 45,
    "color": {
      "en": "brown",
      "de": "Braun"
    },
    "height": 3,
    "weight": 15,
    "cries": {
      "latest": "https:\/\/raw.githubusercontent.com\/PokeAPI\/cries\/main\/cries\/pokemon\/latest\/722.ogg",
      "legacy": null
    },
    "abilities": {
      "en": "Langstrecke",
      "de": "Notd\u00fcnger"
    },
    "type": [
      {
        "en": "grass",
        "de": "Pflanze"
      },
      {
        "en": "flying",
        "de": "Flug"
      }
    ]
  },
  {
    "id": 723,
    "name": "dartrix",
    "names": {
      "en": "dartrix",
      "de": "Arboretoss"
    },
    "generation_id": 7,
    "capture_rate": 45,
    "color": {
      "en": "brown",
      "de": "Braun"
    },
    "height": 7,
    "weight": 160,
    "cries": {
      "latest": "https:\/\/raw.githubusercontent.com\/PokeAPI\/cries\/main\/cries\/pokemon\/latest\/723.ogg",
      "legacy": null
    },
    "abilities": {
      "en": "Langstrecke",
      "de": "Notd\u00fcnger"
    },
    "type": [
      {
        "en": "grass",
        "de": "Pflanze"
      },
      {
        "en": "flying",
        "de": "Flug"
      }
    ]
  },
  {
    "id": 724,
    "name": "decidueye",
    "names": {
      "en": "decidueye",
      "de": "Silvarro"
    },
    "generation_id": 7,
    "capture_rate": 45,
    "color": {
      "en": "brown",
      "de": "Braun"
    },
    "height": 16,
    "weight": 366,
    "cries": {
      "latest": "https:\/\/raw.githubusercontent.com\/PokeAPI\/cries\/main\/cries\/pokemon\/latest\/724.ogg",
      "legacy": null
    },
    "abilities": {
      "en": "Langstrecke",
      "de": "Notd\u00fcnger"
    },
    "type": [
      {
        "en": "grass",
        "de": "Pflanze"
      },
      {
        "en": "ghost",
        "de": "Geist"
      }
    ]
  },
  {
    "id": 725,
    "name": "litten",
    "names": {
      "en": "litten",
      "de": "Flamiau"
    },
    "generation_id": 7,
    "capture_rate": 45,
    "color": {
      "en": "red",
      "de": "Rot"
    },
    "height": 4,
    "weight": 43,
    "cries": {
      "latest": "https:\/\/raw.githubusercontent.com\/PokeAPI\/cries\/main\/cries\/pokemon\/latest\/725.ogg",
      "legacy": null
    },
    "abilities": {
      "en": "Bedroher",
      "de": "Gro\u00dfbrand"
    },
    "type": [
      {
        "en": "fire",
        "de": "Feuer"
      }
    ]
  },
  {
    "id": 726,
    "name": "torracat",
    "names": {
      "en": "torracat",
      "de": "Miezunder"
    },
    "generation_id": 7,
    "capture_rate": 45,
    "color": {
      "en": "red",
      "de": "Rot"
    },
    "height": 7,
    "weight": 250,
    "cries": {
      "latest": "https:\/\/raw.githubusercontent.com\/PokeAPI\/cries\/main\/cries\/pokemon\/latest\/726.ogg",
      "legacy": null
    },
    "abilities": {
      "en": "Bedroher",
      "de": "Gro\u00dfbrand"
    },
    "type": [
      {
        "en": "fire",
        "de": "Feuer"
      }
    ]
  },
  {
    "id": 727,
    "name": "incineroar",
    "names": {
      "en": "incineroar",
      "de": "Fuegro"
    },
    "generation_id": 7,
    "capture_rate": 45,
    "color": {
      "en": "red",
      "de": "Rot"
    },
    "height": 18,
    "weight": 830,
    "cries": {
      "latest": "https:\/\/raw.githubusercontent.com\/PokeAPI\/cries\/main\/cries\/pokemon\/latest\/727.ogg",
      "legacy": null
    },
    "abilities": {
      "en": "Bedroher",
      "de": "Gro\u00dfbrand"
    },
    "type": [
      {
        "en": "fire",
        "de": "Feuer"
      },
      {
        "en": "dark",
        "de": "Unlicht"
      }
    ]
  },
  {
    "id": 728,
    "name": "popplio",
    "names": {
      "en": "popplio",
      "de": "Robball"
    },
    "generation_id": 7,
    "capture_rate": 45,
    "color": {
      "en": "blue",
      "de": "Blau"
    },
    "height": 4,
    "weight": 75,
    "cries": {
      "latest": "https:\/\/raw.githubusercontent.com\/PokeAPI\/cries\/main\/cries\/pokemon\/latest\/728.ogg",
      "legacy": null
    },
    "abilities": {
      "en": "Pl\u00e4tscherstimme",
      "de": "Sturzbach"
    },
    "type": [
      {
        "en": "water",
        "de": "Wasser"
      }
    ]
  },
  {
    "id": 729,
    "name": "brionne",
    "names": {
      "en": "brionne",
      "de": "Marikeck"
    },
    "generation_id": 7,
    "capture_rate": 45,
    "color": {
      "en": "blue",
      "de": "Blau"
    },
    "height": 6,
    "weight": 175,
    "cries": {
      "latest": "https:\/\/raw.githubusercontent.com\/PokeAPI\/cries\/main\/cries\/pokemon\/latest\/729.ogg",
      "legacy": null
    },
    "abilities": {
      "en": "Pl\u00e4tscherstimme",
      "de": "Sturzbach"
    },
    "type": [
      {
        "en": "water",
        "de": "Wasser"
      }
    ]
  },
  {
    "id": 730,
    "name": "primarina",
    "names": {
      "en": "primarina",
      "de": "Primarene"
    },
    "generation_id": 7,
    "capture_rate": 45,
    "color": {
      "en": "blue",
      "de": "Blau"
    },
    "height": 18,
    "weight": 440,
    "cries": {
      "latest": "https:\/\/raw.githubusercontent.com\/PokeAPI\/cries\/main\/cries\/pokemon\/latest\/730.ogg",
      "legacy": null
    },
    "abilities": {
      "en": "Pl\u00e4tscherstimme",
      "de": "Sturzbach"
    },
    "type": [
      {
        "en": "water",
        "de": "Wasser"
      },
      {
        "en": "fairy",
        "de": "Fee"
      }
    ]
  },
  {
    "id": 731,
    "name": "pikipek",
    "names": {
      "en": "pikipek",
      "de": "Peppeck"
    },
    "generation_id": 7,
    "capture_rate": 255,
    "color": {
      "en": "black",
      "de": "Schwarz"
    },
    "height": 3,
    "weight": 12,
    "cries": {
      "latest": "https:\/\/raw.githubusercontent.com\/PokeAPI\/cries\/main\/cries\/pokemon\/latest\/731.ogg",
      "legacy": null
    },
    "abilities": {
      "en": "Wertelink",
      "de": "Adlerauge"
    },
    "type": [
      {
        "en": "normal",
        "de": "Normal"
      },
      {
        "en": "flying",
        "de": "Flug"
      }
    ]
  },
  {
    "id": 732,
    "name": "trumbeak",
    "names": {
      "en": "trumbeak",
      "de": "Trompeck"
    },
    "generation_id": 7,
    "capture_rate": 120,
    "color": {
      "en": "black",
      "de": "Schwarz"
    },
    "height": 6,
    "weight": 148,
    "cries": {
      "latest": "https:\/\/raw.githubusercontent.com\/PokeAPI\/cries\/main\/cries\/pokemon\/latest\/732.ogg",
      "legacy": null
    },
    "abilities": {
      "en": "Wertelink",
      "de": "Adlerauge"
    },
    "type": [
      {
        "en": "normal",
        "de": "Normal"
      },
      {
        "en": "flying",
        "de": "Flug"
      }
    ]
  },
  {
    "id": 733,
    "name": "toucannon",
    "names": {
      "en": "toucannon",
      "de": "Tukanon"
    },
    "generation_id": 7,
    "capture_rate": 45,
    "color": {
      "en": "black",
      "de": "Schwarz"
    },
    "height": 11,
    "weight": 260,
    "cries": {
      "latest": "https:\/\/raw.githubusercontent.com\/PokeAPI\/cries\/main\/cries\/pokemon\/latest\/733.ogg",
      "legacy": null
    },
    "abilities": {
      "en": "Wertelink",
      "de": "Adlerauge"
    },
    "type": [
      {
        "en": "normal",
        "de": "Normal"
      },
      {
        "en": "flying",
        "de": "Flug"
      }
    ]
  },
  {
    "id": 734,
    "name": "yungoos",
    "names": {
      "en": "yungoos",
      "de": "Mangunior"
    },
    "generation_id": 7,
    "capture_rate": 255,
    "color": {
      "en": "brown",
      "de": "Braun"
    },
    "height": 4,
    "weight": 60,
    "cries": {
      "latest": "https:\/\/raw.githubusercontent.com\/PokeAPI\/cries\/main\/cries\/pokemon\/latest\/734.ogg",
      "legacy": null
    },
    "abilities": {
      "en": "Titankiefer",
      "de": "Beschattung"
    },
    "type": [
      {
        "en": "normal",
        "de": "Normal"
      }
    ]
  },
  {
    "id": 735,
    "name": "gumshoos",
    "names": {
      "en": "gumshoos",
      "de": "Manguspektor"
    },
    "generation_id": 7,
    "capture_rate": 127,
    "color": {
      "en": "brown",
      "de": "Braun"
    },
    "height": 7,
    "weight": 142,
    "cries": {
      "latest": "https:\/\/raw.githubusercontent.com\/PokeAPI\/cries\/main\/cries\/pokemon\/latest\/735.ogg",
      "legacy": null
    },
    "abilities": {
      "en": "Titankiefer",
      "de": "Beschattung"
    },
    "type": [
      {
        "en": "normal",
        "de": "Normal"
      }
    ]
  },
  {
    "id": 736,
    "name": "grubbin",
    "names": {
      "en": "grubbin",
      "de": "Mabula"
    },
    "generation_id": 7,
    "capture_rate": 255,
    "color": {
      "en": "gray",
      "de": "Grau"
    },
    "height": 4,
    "weight": 44,
    "cries": {
      "latest": "https:\/\/raw.githubusercontent.com\/PokeAPI\/cries\/main\/cries\/pokemon\/latest\/736.ogg",
      "legacy": null
    },
    "abilities": {
      "en": null,
      "de": "Hexaplaga"
    },
    "type": [
      {
        "en": "bug",
        "de": "K\u00e4fer"
      }
    ]
  },
  {
    "id": 737,
    "name": "charjabug",
    "names": {
      "en": "charjabug",
      "de": "Akkup"
    },
    "generation_id": 7,
    "capture_rate": 120,
    "color": {
      "en": "green",
      "de": "Gr\u00fcn"
    },
    "height": 5,
    "weight": 105,
    "cries": {
      "latest": "https:\/\/raw.githubusercontent.com\/PokeAPI\/cries\/main\/cries\/pokemon\/latest\/737.ogg",
      "legacy": null
    },
    "abilities": {
      "en": null,
      "de": "Batterie"
    },
    "type": [
      {
        "en": "bug",
        "de": "K\u00e4fer"
      },
      {
        "en": "electric",
        "de": "Elektro"
      }
    ]
  },
  {
    "id": 738,
    "name": "vikavolt",
    "names": {
      "en": "vikavolt",
      "de": "Donarion"
    },
    "generation_id": 7,
    "capture_rate": 45,
    "color": {
      "en": "blue",
      "de": "Blau"
    },
    "height": 15,
    "weight": 450,
    "cries": {
      "latest": "https:\/\/raw.githubusercontent.com\/PokeAPI\/cries\/main\/cries\/pokemon\/latest\/738.ogg",
      "legacy": null
    },
    "abilities": {
      "en": null,
      "de": "Schwebe"
    },
    "type": [
      {
        "en": "bug",
        "de": "K\u00e4fer"
      },
      {
        "en": "electric",
        "de": "Elektro"
      }
    ]
  },
  {
    "id": 739,
    "name": "crabrawler",
    "names": {
      "en": "crabrawler",
      "de": "Krabbox"
    },
    "generation_id": 7,
    "capture_rate": 225,
    "color": {
      "en": "purple",
      "de": "Violett"
    },
    "height": 6,
    "weight": 70,
    "cries": {
      "latest": "https:\/\/raw.githubusercontent.com\/PokeAPI\/cries\/main\/cries\/pokemon\/latest\/739.ogg",
      "legacy": null
    },
    "abilities": {
      "en": "Eisenfaust",
      "de": "Scherenmacht"
    },
    "type": [
      {
        "en": "fighting",
        "de": "Kampf"
      }
    ]
  },
  {
    "id": 740,
    "name": "crabominable",
    "names": {
      "en": "crabominable",
      "de": "Krawell"
    },
    "generation_id": 7,
    "capture_rate": 60,
    "color": {
      "en": "white",
      "de": "Wei\u00df"
    },
    "height": 17,
    "weight": 1800,
    "cries": {
      "latest": "https:\/\/raw.githubusercontent.com\/PokeAPI\/cries\/main\/cries\/pokemon\/latest\/740.ogg",
      "legacy": null
    },
    "abilities": {
      "en": "Eisenfaust",
      "de": "Scherenmacht"
    },
    "type": [
      {
        "en": "fighting",
        "de": "Kampf"
      },
      {
        "en": "ice",
        "de": "Eis"
      }
    ]
  },
  {
    "id": 741,
    "name": "oricorio",
    "names": {
      "en": "oricorio",
      "de": "Choreogel"
    },
    "generation_id": 7,
    "capture_rate": 45,
    "color": {
      "en": "red",
      "de": "Rot"
    },
    "height": 6,
    "weight": 34,
    "cries": {
      "latest": "https:\/\/raw.githubusercontent.com\/PokeAPI\/cries\/main\/cries\/pokemon\/latest\/741.ogg",
      "legacy": null
    },
    "abilities": {
      "en": null,
      "de": "T\u00e4nzer"
    },
    "type": [
      {
        "en": "fire",
        "de": "Feuer"
      },
      {
        "en": "flying",
        "de": "Flug"
      }
    ]
  },
  {
    "id": 742,
    "name": "cutiefly",
    "names": {
      "en": "cutiefly",
      "de": "Wommel"
    },
    "generation_id": 7,
    "capture_rate": 190,
    "color": {
      "en": "yellow",
      "de": "Gelb"
    },
    "height": 1,
    "weight": 2,
    "cries": {
      "latest": "https:\/\/raw.githubusercontent.com\/PokeAPI\/cries\/main\/cries\/pokemon\/latest\/742.ogg",
      "legacy": null
    },
    "abilities": {
      "en": "Puderabwehr",
      "de": "Honigmaul"
    },
    "type": [
      {
        "en": "bug",
        "de": "K\u00e4fer"
      },
      {
        "en": "fairy",
        "de": "Fee"
      }
    ]
  },
  {
    "id": 743,
    "name": "ribombee",
    "names": {
      "en": "ribombee",
      "de": "Bandelby"
    },
    "generation_id": 7,
    "capture_rate": 75,
    "color": {
      "en": "yellow",
      "de": "Gelb"
    },
    "height": 2,
    "weight": 5,
    "cries": {
      "latest": "https:\/\/raw.githubusercontent.com\/PokeAPI\/cries\/main\/cries\/pokemon\/latest\/743.ogg",
      "legacy": null
    },
    "abilities": {
      "en": "Puderabwehr",
      "de": "Honigmaul"
    },
    "type": [
      {
        "en": "bug",
        "de": "K\u00e4fer"
      },
      {
        "en": "fairy",
        "de": "Fee"
      }
    ]
  },
  {
    "id": 744,
    "name": "rockruff",
    "names": {
      "en": "rockruff",
      "de": "Wuffels"
    },
    "generation_id": 7,
    "capture_rate": 190,
    "color": {
      "en": "brown",
      "de": "Braun"
    },
    "height": 5,
    "weight": 92,
    "cries": {
      "latest": "https:\/\/raw.githubusercontent.com\/PokeAPI\/cries\/main\/cries\/pokemon\/latest\/744.ogg",
      "legacy": null
    },
    "abilities": {
      "en": "Munterkeit",
      "de": "Adlerauge"
    },
    "type": [
      {
        "en": "rock",
        "de": "Gestein"
      }
    ]
  },
  {
    "id": 745,
    "name": "lycanroc",
    "names": {
      "en": "lycanroc",
      "de": "Wolwerock"
    },
    "generation_id": 7,
    "capture_rate": 90,
    "color": {
      "en": "brown",
      "de": "Braun"
    },
    "height": 8,
    "weight": 250,
    "cries": {
      "latest": "https:\/\/raw.githubusercontent.com\/PokeAPI\/cries\/main\/cries\/pokemon\/latest\/745.ogg",
      "legacy": null
    },
    "abilities": {
      "en": "Sandscharrer",
      "de": "Adlerauge"
    },
    "type": [
      {
        "en": "rock",
        "de": "Gestein"
      }
    ]
  },
  {
    "id": 746,
    "name": "wishiwashi",
    "names": {
      "en": "wishiwashi",
      "de": "Lusardin"
    },
    "generation_id": 7,
    "capture_rate": 60,
    "color": {
      "en": "blue",
      "de": "Blau"
    },
    "height": 2,
    "weight": 3,
    "cries": {
      "latest": "https:\/\/raw.githubusercontent.com\/PokeAPI\/cries\/main\/cries\/pokemon\/latest\/746.ogg",
      "legacy": null
    },
    "abilities": {
      "en": null,
      "de": "Fischschwarm"
    },
    "type": [
      {
        "en": "water",
        "de": "Wasser"
      }
    ]
  },
  {
    "id": 747,
    "name": "mareanie",
    "names": {
      "en": "mareanie",
      "de": "Garstella"
    },
    "generation_id": 7,
    "capture_rate": 190,
    "color": {
      "en": "blue",
      "de": "Blau"
    },
    "height": 4,
    "weight": 80,
    "cries": {
      "latest": "https:\/\/raw.githubusercontent.com\/PokeAPI\/cries\/main\/cries\/pokemon\/latest\/747.ogg",
      "legacy": null
    },
    "abilities": {
      "en": "Flexibilit\u00e4t",
      "de": "Qu\u00e4lerei"
    },
    "type": [
      {
        "en": "poison",
        "de": "Gift"
      },
      {
        "en": "water",
        "de": "Wasser"
      }
    ]
  },
  {
    "id": 748,
    "name": "toxapex",
    "names": {
      "en": "toxapex",
      "de": "Aggrostella"
    },
    "generation_id": 7,
    "capture_rate": 75,
    "color": {
      "en": "blue",
      "de": "Blau"
    },
    "height": 7,
    "weight": 145,
    "cries": {
      "latest": "https:\/\/raw.githubusercontent.com\/PokeAPI\/cries\/main\/cries\/pokemon\/latest\/748.ogg",
      "legacy": null
    },
    "abilities": {
      "en": "Flexibilit\u00e4t",
      "de": "Qu\u00e4lerei"
    },
    "type": [
      {
        "en": "poison",
        "de": "Gift"
      },
      {
        "en": "water",
        "de": "Wasser"
      }
    ]
  },
  {
    "id": 749,
    "name": "mudbray",
    "names": {
      "en": "mudbray",
      "de": "Pampuli"
    },
    "generation_id": 7,
    "capture_rate": 190,
    "color": {
      "en": "brown",
      "de": "Braun"
    },
    "height": 10,
    "weight": 1100,
    "cries": {
      "latest": "https:\/\/raw.githubusercontent.com\/PokeAPI\/cries\/main\/cries\/pokemon\/latest\/749.ogg",
      "legacy": null
    },
    "abilities": {
      "en": "Z\u00e4higkeit",
      "de": "Tempomacher"
    },
    "type": [
      {
        "en": "ground",
        "de": "Boden"
      }
    ]
  },
  {
    "id": 750,
    "name": "mudsdale",
    "names": {
      "en": "mudsdale",
      "de": "Pampross"
    },
    "generation_id": 7,
    "capture_rate": 60,
    "color": {
      "en": "brown",
      "de": "Braun"
    },
    "height": 25,
    "weight": 9200,
    "cries": {
      "latest": "https:\/\/raw.githubusercontent.com\/PokeAPI\/cries\/main\/cries\/pokemon\/latest\/750.ogg",
      "legacy": null
    },
    "abilities": {
      "en": "Z\u00e4higkeit",
      "de": "Tempomacher"
    },
    "type": [
      {
        "en": "ground",
        "de": "Boden"
      }
    ]
  },
  {
    "id": 751,
    "name": "dewpider",
    "names": {
      "en": "dewpider",
      "de": "Araqua"
    },
    "generation_id": 7,
    "capture_rate": 200,
    "color": {
      "en": "green",
      "de": "Gr\u00fcn"
    },
    "height": 3,
    "weight": 40,
    "cries": {
      "latest": "https:\/\/raw.githubusercontent.com\/PokeAPI\/cries\/main\/cries\/pokemon\/latest\/751.ogg",
      "legacy": null
    },
    "abilities": {
      "en": "H2O-Absorber",
      "de": "Wasserblase"
    },
    "type": [
      {
        "en": "water",
        "de": "Wasser"
      },
      {
        "en": "bug",
        "de": "K\u00e4fer"
      }
    ]
  },
  {
    "id": 752,
    "name": "araquanid",
    "names": {
      "en": "araquanid",
      "de": "Aranestro"
    },
    "generation_id": 7,
    "capture_rate": 100,
    "color": {
      "en": "green",
      "de": "Gr\u00fcn"
    },
    "height": 18,
    "weight": 820,
    "cries": {
      "latest": "https:\/\/raw.githubusercontent.com\/PokeAPI\/cries\/main\/cries\/pokemon\/latest\/752.ogg",
      "legacy": null
    },
    "abilities": {
      "en": "H2O-Absorber",
      "de": "Wasserblase"
    },
    "type": [
      {
        "en": "water",
        "de": "Wasser"
      },
      {
        "en": "bug",
        "de": "K\u00e4fer"
      }
    ]
  },
  {
    "id": 753,
    "name": "fomantis",
    "names": {
      "en": "fomantis",
      "de": "Imantis"
    },
    "generation_id": 7,
    "capture_rate": 190,
    "color": {
      "en": "pink",
      "de": "Rosa"
    },
    "height": 3,
    "weight": 15,
    "cries": {
      "latest": "https:\/\/raw.githubusercontent.com\/PokeAPI\/cries\/main\/cries\/pokemon\/latest\/753.ogg",
      "legacy": null
    },
    "abilities": {
      "en": "Umkehrung",
      "de": "Floraschild"
    },
    "type": [
      {
        "en": "grass",
        "de": "Pflanze"
      }
    ]
  },
  {
    "id": 754,
    "name": "lurantis",
    "names": {
      "en": "lurantis",
      "de": "Mantidea"
    },
    "generation_id": 7,
    "capture_rate": 75,
    "color": {
      "en": "pink",
      "de": "Rosa"
    },
    "height": 9,
    "weight": 185,
    "cries": {
      "latest": "https:\/\/raw.githubusercontent.com\/PokeAPI\/cries\/main\/cries\/pokemon\/latest\/754.ogg",
      "legacy": null
    },
    "abilities": {
      "en": "Umkehrung",
      "de": "Floraschild"
    },
    "type": [
      {
        "en": "grass",
        "de": "Pflanze"
      }
    ]
  },
  {
    "id": 755,
    "name": "morelull",
    "names": {
      "en": "morelull",
      "de": "Bubungus"
    },
    "generation_id": 7,
    "capture_rate": 190,
    "color": {
      "en": "purple",
      "de": "Violett"
    },
    "height": 2,
    "weight": 15,
    "cries": {
      "latest": "https:\/\/raw.githubusercontent.com\/PokeAPI\/cries\/main\/cries\/pokemon\/latest\/755.ogg",
      "legacy": null
    },
    "abilities": {
      "en": "Sporenwirt",
      "de": "Erleuchtung"
    },
    "type": [
      {
        "en": "grass",
        "de": "Pflanze"
      },
      {
        "en": "fairy",
        "de": "Fee"
      }
    ]
  },
  {
    "id": 756,
    "name": "shiinotic",
    "names": {
      "en": "shiinotic",
      "de": "Lamellux"
    },
    "generation_id": 7,
    "capture_rate": 75,
    "color": {
      "en": "purple",
      "de": "Violett"
    },
    "height": 10,
    "weight": 115,
    "cries": {
      "latest": "https:\/\/raw.githubusercontent.com\/PokeAPI\/cries\/main\/cries\/pokemon\/latest\/756.ogg",
      "legacy": null
    },
    "abilities": {
      "en": "Sporenwirt",
      "de": "Erleuchtung"
    },
    "type": [
      {
        "en": "grass",
        "de": "Pflanze"
      },
      {
        "en": "fairy",
        "de": "Fee"
      }
    ]
  },
  {
    "id": 757,
    "name": "salandit",
    "names": {
      "en": "salandit",
      "de": "Molunk"
    },
    "generation_id": 7,
    "capture_rate": 120,
    "color": {
      "en": "black",
      "de": "Schwarz"
    },
    "height": 6,
    "weight": 48,
    "cries": {
      "latest": "https:\/\/raw.githubusercontent.com\/PokeAPI\/cries\/main\/cries\/pokemon\/latest\/757.ogg",
      "legacy": null
    },
    "abilities": {
      "en": "D\u00f6sigkeit",
      "de": "Korrosion"
    },
    "type": [
      {
        "en": "poison",
        "de": "Gift"
      },
      {
        "en": "fire",
        "de": "Feuer"
      }
    ]
  },
  {
    "id": 758,
    "name": "salazzle",
    "names": {
      "en": "salazzle",
      "de": "Amfira"
    },
    "generation_id": 7,
    "capture_rate": 45,
    "color": {
      "en": "black",
      "de": "Schwarz"
    },
    "height": 12,
    "weight": 222,
    "cries": {
      "latest": "https:\/\/raw.githubusercontent.com\/PokeAPI\/cries\/main\/cries\/pokemon\/latest\/758.ogg",
      "legacy": null
    },
    "abilities": {
      "en": "D\u00f6sigkeit",
      "de": "Korrosion"
    },
    "type": [
      {
        "en": "poison",
        "de": "Gift"
      },
      {
        "en": "fire",
        "de": "Feuer"
      }
    ]
  },
  {
    "id": 759,
    "name": "stufful",
    "names": {
      "en": "stufful",
      "de": "Velursi"
    },
    "generation_id": 7,
    "capture_rate": 140,
    "color": {
      "en": "pink",
      "de": "Rosa"
    },
    "height": 5,
    "weight": 68,
    "cries": {
      "latest": "https:\/\/raw.githubusercontent.com\/PokeAPI\/cries\/main\/cries\/pokemon\/latest\/759.ogg",
      "legacy": null
    },
    "abilities": {
      "en": "Tollpatsch",
      "de": "Flauschigkeit"
    },
    "type": [
      {
        "en": "normal",
        "de": "Normal"
      },
      {
        "en": "fighting",
        "de": "Kampf"
      }
    ]
  },
  {
    "id": 760,
    "name": "bewear",
    "names": {
      "en": "bewear",
      "de": "Kosturso"
    },
    "generation_id": 7,
    "capture_rate": 70,
    "color": {
      "en": "pink",
      "de": "Rosa"
    },
    "height": 21,
    "weight": 1350,
    "cries": {
      "latest": "https:\/\/raw.githubusercontent.com\/PokeAPI\/cries\/main\/cries\/pokemon\/latest\/760.ogg",
      "legacy": null
    },
    "abilities": {
      "en": "Tollpatsch",
      "de": "Flauschigkeit"
    },
    "type": [
      {
        "en": "normal",
        "de": "Normal"
      },
      {
        "en": "fighting",
        "de": "Kampf"
      }
    ]
  },
  {
    "id": 761,
    "name": "bounsweet",
    "names": {
      "en": "bounsweet",
      "de": "Frubberl"
    },
    "generation_id": 7,
    "capture_rate": 235,
    "color": {
      "en": "purple",
      "de": "Violett"
    },
    "height": 3,
    "weight": 32,
    "cries": {
      "latest": "https:\/\/raw.githubusercontent.com\/PokeAPI\/cries\/main\/cries\/pokemon\/latest\/761.ogg",
      "legacy": null
    },
    "abilities": {
      "en": "D\u00f6sigkeit",
      "de": "Floraschild"
    },
    "type": [
      {
        "en": "grass",
        "de": "Pflanze"
      }
    ]
  },
  {
    "id": 762,
    "name": "steenee",
    "names": {
      "en": "steenee",
      "de": "Frubaila"
    },
    "generation_id": 7,
    "capture_rate": 120,
    "color": {
      "en": "purple",
      "de": "Violett"
    },
    "height": 7,
    "weight": 82,
    "cries": {
      "latest": "https:\/\/raw.githubusercontent.com\/PokeAPI\/cries\/main\/cries\/pokemon\/latest\/762.ogg",
      "legacy": null
    },
    "abilities": {
      "en": "D\u00f6sigkeit",
      "de": "Floraschild"
    },
    "type": [
      {
        "en": "grass",
        "de": "Pflanze"
      }
    ]
  },
  {
    "id": 763,
    "name": "tsareena",
    "names": {
      "en": "tsareena",
      "de": "Fruyal"
    },
    "generation_id": 7,
    "capture_rate": 45,
    "color": {
      "en": "purple",
      "de": "Violett"
    },
    "height": 12,
    "weight": 214,
    "cries": {
      "latest": "https:\/\/raw.githubusercontent.com\/PokeAPI\/cries\/main\/cries\/pokemon\/latest\/763.ogg",
      "legacy": null
    },
    "abilities": {
      "en": "Majest\u00e4t",
      "de": "Floraschild"
    },
    "type": [
      {
        "en": "grass",
        "de": "Pflanze"
      }
    ]
  },
  {
    "id": 764,
    "name": "comfey",
    "names": {
      "en": "comfey",
      "de": "Curelei"
    },
    "generation_id": 7,
    "capture_rate": 60,
    "color": {
      "en": "green",
      "de": "Gr\u00fcn"
    },
    "height": 1,
    "weight": 3,
    "cries": {
      "latest": "https:\/\/raw.githubusercontent.com\/PokeAPI\/cries\/main\/cries\/pokemon\/latest\/764.ogg",
      "legacy": null
    },
    "abilities": {
      "en": "Heilwandel",
      "de": "Bl\u00fctenh\u00fclle"
    },
    "type": [
      {
        "en": "fairy",
        "de": "Fee"
      }
    ]
  },
  {
    "id": 765,
    "name": "oranguru",
    "names": {
      "en": "oranguru",
      "de": "Kommandutan"
    },
    "generation_id": 7,
    "capture_rate": 45,
    "color": {
      "en": "white",
      "de": "Wei\u00df"
    },
    "height": 15,
    "weight": 760,
    "cries": {
      "latest": "https:\/\/raw.githubusercontent.com\/PokeAPI\/cries\/main\/cries\/pokemon\/latest\/765.ogg",
      "legacy": null
    },
    "abilities": {
      "en": "Telepathie",
      "de": "Konzentrator"
    },
    "type": [
      {
        "en": "normal",
        "de": "Normal"
      },
      {
        "en": "psychic",
        "de": "Psycho"
      }
    ]
  },
  {
    "id": 766,
    "name": "passimian",
    "names": {
      "en": "passimian",
      "de": "Quartermak"
    },
    "generation_id": 7,
    "capture_rate": 45,
    "color": {
      "en": "white",
      "de": "Wei\u00df"
    },
    "height": 20,
    "weight": 828,
    "cries": {
      "latest": "https:\/\/raw.githubusercontent.com\/PokeAPI\/cries\/main\/cries\/pokemon\/latest\/766.ogg",
      "legacy": null
    },
    "abilities": {
      "en": "Siegeswille",
      "de": "Receiver"
    },
    "type": [
      {
        "en": "fighting",
        "de": "Kampf"
      }
    ]
  },
  {
    "id": 767,
    "name": "wimpod",
    "names": {
      "en": "wimpod",
      "de": "Rei\u00dflaus"
    },
    "generation_id": 7,
    "capture_rate": 90,
    "color": {
      "en": "gray",
      "de": "Grau"
    },
    "height": 5,
    "weight": 120,
    "cries": {
      "latest": "https:\/\/raw.githubusercontent.com\/PokeAPI\/cries\/main\/cries\/pokemon\/latest\/767.ogg",
      "legacy": null
    },
    "abilities": {
      "en": null,
      "de": "Rei\u00dfaus"
    },
    "type": [
      {
        "en": "bug",
        "de": "K\u00e4fer"
      },
      {
        "en": "water",
        "de": "Wasser"
      }
    ]
  },
  {
    "id": 768,
    "name": "golisopod",
    "names": {
      "en": "golisopod",
      "de": "Tectass"
    },
    "generation_id": 7,
    "capture_rate": 45,
    "color": {
      "en": "gray",
      "de": "Grau"
    },
    "height": 20,
    "weight": 1080,
    "cries": {
      "latest": "https:\/\/raw.githubusercontent.com\/PokeAPI\/cries\/main\/cries\/pokemon\/latest\/768.ogg",
      "legacy": null
    },
    "abilities": {
      "en": null,
      "de": "R\u00fcckzug"
    },
    "type": [
      {
        "en": "bug",
        "de": "K\u00e4fer"
      },
      {
        "en": "water",
        "de": "Wasser"
      }
    ]
  },
  {
    "id": 769,
    "name": "sandygast",
    "names": {
      "en": "sandygast",
      "de": "Sankabuh"
    },
    "generation_id": 7,
    "capture_rate": 140,
    "color": {
      "en": "brown",
      "de": "Braun"
    },
    "height": 5,
    "weight": 700,
    "cries": {
      "latest": "https:\/\/raw.githubusercontent.com\/PokeAPI\/cries\/main\/cries\/pokemon\/latest\/769.ogg",
      "legacy": null
    },
    "abilities": {
      "en": "Sandschleier",
      "de": "Verklumpen"
    },
    "type": [
      {
        "en": "ghost",
        "de": "Geist"
      },
      {
        "en": "ground",
        "de": "Boden"
      }
    ]
  },
  {
    "id": 770,
    "name": "palossand",
    "names": {
      "en": "palossand",
      "de": "Colossand"
    },
    "generation_id": 7,
    "capture_rate": 60,
    "color": {
      "en": "brown",
      "de": "Braun"
    },
    "height": 13,
    "weight": 2500,
    "cries": {
      "latest": "https:\/\/raw.githubusercontent.com\/PokeAPI\/cries\/main\/cries\/pokemon\/latest\/770.ogg",
      "legacy": null
    },
    "abilities": {
      "en": "Sandschleier",
      "de": "Verklumpen"
    },
    "type": [
      {
        "en": "ghost",
        "de": "Geist"
      },
      {
        "en": "ground",
        "de": "Boden"
      }
    ]
  },
  {
    "id": 771,
    "name": "pyukumuku",
    "names": {
      "en": "pyukumuku",
      "de": "Gufa"
    },
    "generation_id": 7,
    "capture_rate": 60,
    "color": {
      "en": "black",
      "de": "Schwarz"
    },
    "height": 3,
    "weight": 12,
    "cries": {
      "latest": "https:\/\/raw.githubusercontent.com\/PokeAPI\/cries\/main\/cries\/pokemon\/latest\/771.ogg",
      "legacy": null
    },
    "abilities": {
      "en": "Unkenntnis",
      "de": "Magenkrempler"
    },
    "type": [
      {
        "en": "water",
        "de": "Wasser"
      }
    ]
  },
  {
    "id": 772,
    "name": "type-null",
    "names": {
      "en": "type-null",
      "de": "Typ:Null"
    },
    "generation_id": 7,
    "capture_rate": 3,
    "color": {
      "en": "gray",
      "de": "Grau"
    },
    "height": 19,
    "weight": 1205,
    "cries": {
      "latest": "https:\/\/raw.githubusercontent.com\/PokeAPI\/cries\/main\/cries\/pokemon\/latest\/772.ogg",
      "legacy": null
    },
    "abilities": {
      "en": null,
      "de": "Kampfpanzer"
    },
    "type": [
      {
        "en": "normal",
        "de": "Normal"
      }
    ]
  },
  {
    "id": 773,
    "name": "silvally",
    "names": {
      "en": "silvally",
      "de": "Amigento"
    },
    "generation_id": 7,
    "capture_rate": 3,
    "color": {
      "en": "gray",
      "de": "Grau"
    },
    "height": 23,
    "weight": 1005,
    "cries": {
      "latest": "https:\/\/raw.githubusercontent.com\/PokeAPI\/cries\/main\/cries\/pokemon\/latest\/773.ogg",
      "legacy": null
    },
    "abilities": {
      "en": null,
      "de": "Alpha-System"
    },
    "type": [
      {
        "en": "normal",
        "de": "Normal"
      }
    ]
  },
  {
    "id": 774,
    "name": "minior",
    "names": {
      "en": "minior",
      "de": "Meteno"
    },
    "generation_id": 7,
    "capture_rate": 30,
    "color": {
      "en": "brown",
      "de": "Braun"
    },
    "height": 3,
    "weight": 400,
    "cries": {
      "latest": "https:\/\/raw.githubusercontent.com\/PokeAPI\/cries\/main\/cries\/pokemon\/latest\/774.ogg",
      "legacy": null
    },
    "abilities": {
      "en": null,
      "de": "Limitschild"
    },
    "type": [
      {
        "en": "rock",
        "de": "Gestein"
      },
      {
        "en": "flying",
        "de": "Flug"
      }
    ]
  },
  {
    "id": 775,
    "name": "komala",
    "names": {
      "en": "komala",
      "de": "Koalelu"
    },
    "generation_id": 7,
    "capture_rate": 45,
    "color": {
      "en": "blue",
      "de": "Blau"
    },
    "height": 4,
    "weight": 199,
    "cries": {
      "latest": "https:\/\/raw.githubusercontent.com\/PokeAPI\/cries\/main\/cries\/pokemon\/latest\/775.ogg",
      "legacy": null
    },
    "abilities": {
      "en": null,
      "de": "Dauerschlaf"
    },
    "type": [
      {
        "en": "normal",
        "de": "Normal"
      }
    ]
  },
  {
    "id": 776,
    "name": "turtonator",
    "names": {
      "en": "turtonator",
      "de": "Tortunator"
    },
    "generation_id": 7,
    "capture_rate": 70,
    "color": {
      "en": "red",
      "de": "Rot"
    },
    "height": 20,
    "weight": 2120,
    "cries": {
      "latest": "https:\/\/raw.githubusercontent.com\/PokeAPI\/cries\/main\/cries\/pokemon\/latest\/776.ogg",
      "legacy": null
    },
    "abilities": {
      "en": null,
      "de": "Panzerhaut"
    },
    "type": [
      {
        "en": "fire",
        "de": "Feuer"
      },
      {
        "en": "dragon",
        "de": "Drache"
      }
    ]
  },
  {
    "id": 777,
    "name": "togedemaru",
    "names": {
      "en": "togedemaru",
      "de": "Togedemaru"
    },
    "generation_id": 7,
    "capture_rate": 180,
    "color": {
      "en": "gray",
      "de": "Grau"
    },
    "height": 3,
    "weight": 33,
    "cries": {
      "latest": "https:\/\/raw.githubusercontent.com\/PokeAPI\/cries\/main\/cries\/pokemon\/latest\/777.ogg",
      "legacy": null
    },
    "abilities": {
      "en": "Blitzf\u00e4nger",
      "de": "Eisenstachel"
    },
    "type": [
      {
        "en": "electric",
        "de": "Elektro"
      },
      {
        "en": "steel",
        "de": "Stahl"
      }
    ]
  },
  {
    "id": 778,
    "name": "mimikyu",
    "names": {
      "en": "mimikyu",
      "de": "Mimigma"
    },
    "generation_id": 7,
    "capture_rate": 45,
    "color": {
      "en": "yellow",
      "de": "Gelb"
    },
    "height": 2,
    "weight": 7,
    "cries": {
      "latest": "https:\/\/raw.githubusercontent.com\/PokeAPI\/cries\/main\/cries\/pokemon\/latest\/778.ogg",
      "legacy": null
    },
    "abilities": {
      "en": null,
      "de": "Kost\u00fcmspuk"
    },
    "type": [
      {
        "en": "ghost",
        "de": "Geist"
      },
      {
        "en": "fairy",
        "de": "Fee"
      }
    ]
  },
  {
    "id": 779,
    "name": "bruxish",
    "names": {
      "en": "bruxish",
      "de": "Knirfish"
    },
    "generation_id": 7,
    "capture_rate": 80,
    "color": {
      "en": "pink",
      "de": "Rosa"
    },
    "height": 9,
    "weight": 190,
    "cries": {
      "latest": "https:\/\/raw.githubusercontent.com\/PokeAPI\/cries\/main\/cries\/pokemon\/latest\/779.ogg",
      "legacy": null
    },
    "abilities": {
      "en": "Titankiefer",
      "de": "Buntk\u00f6rper"
    },
    "type": [
      {
        "en": "water",
        "de": "Wasser"
      },
      {
        "en": "psychic",
        "de": "Psycho"
      }
    ]
  },
  {
    "id": 780,
    "name": "drampa",
    "names": {
      "en": "drampa",
      "de": "Sen-Long"
    },
    "generation_id": 7,
    "capture_rate": 70,
    "color": {
      "en": "white",
      "de": "Wei\u00df"
    },
    "height": 30,
    "weight": 1850,
    "cries": {
      "latest": "https:\/\/raw.githubusercontent.com\/PokeAPI\/cries\/main\/cries\/pokemon\/latest\/780.ogg",
      "legacy": null
    },
    "abilities": {
      "en": "Vegetarier",
      "de": "Wutausbruch"
    },
    "type": [
      {
        "en": "normal",
        "de": "Normal"
      },
      {
        "en": "dragon",
        "de": "Drache"
      }
    ]
  },
  {
    "id": 781,
    "name": "dhelmise",
    "names": {
      "en": "dhelmise",
      "de": "Moruda"
    },
    "generation_id": 7,
    "capture_rate": 25,
    "color": {
      "en": "green",
      "de": "Gr\u00fcn"
    },
    "height": 39,
    "weight": 2100,
    "cries": {
      "latest": "https:\/\/raw.githubusercontent.com\/PokeAPI\/cries\/main\/cries\/pokemon\/latest\/781.ogg",
      "legacy": null
    },
    "abilities": {
      "en": null,
      "de": "Stahlprofi"
    },
    "type": [
      {
        "en": "ghost",
        "de": "Geist"
      },
      {
        "en": "grass",
        "de": "Pflanze"
      }
    ]
  },
  {
    "id": 782,
    "name": "jangmo-o",
    "names": {
      "en": "jangmo-o",
      "de": "Miniras"
    },
    "generation_id": 7,
    "capture_rate": 45,
    "color": {
      "en": "gray",
      "de": "Grau"
    },
    "height": 6,
    "weight": 297,
    "cries": {
      "latest": "https:\/\/raw.githubusercontent.com\/PokeAPI\/cries\/main\/cries\/pokemon\/latest\/782.ogg",
      "legacy": null
    },
    "abilities": {
      "en": "L\u00e4rmschutz",
      "de": "Kugelsicher"
    },
    "type": [
      {
        "en": "dragon",
        "de": "Drache"
      }
    ]
  },
  {
    "id": 783,
    "name": "hakamo-o",
    "names": {
      "en": "hakamo-o",
      "de": "Mediras"
    },
    "generation_id": 7,
    "capture_rate": 45,
    "color": {
      "en": "gray",
      "de": "Grau"
    },
    "height": 12,
    "weight": 470,
    "cries": {
      "latest": "https:\/\/raw.githubusercontent.com\/PokeAPI\/cries\/main\/cries\/pokemon\/latest\/783.ogg",
      "legacy": null
    },
    "abilities": {
      "en": "L\u00e4rmschutz",
      "de": "Kugelsicher"
    },
    "type": [
      {
        "en": "dragon",
        "de": "Drache"
      },
      {
        "en": "fighting",
        "de": "Kampf"
      }
    ]
  },
  {
    "id": 784,
    "name": "kommo-o",
    "names": {
      "en": "kommo-o",
      "de": "Grandiras"
    },
    "generation_id": 7,
    "capture_rate": 45,
    "color": {
      "en": "gray",
      "de": "Grau"
    },
    "height": 16,
    "weight": 782,
    "cries": {
      "latest": "https:\/\/raw.githubusercontent.com\/PokeAPI\/cries\/main\/cries\/pokemon\/latest\/784.ogg",
      "legacy": null
    },
    "abilities": {
      "en": "L\u00e4rmschutz",
      "de": "Kugelsicher"
    },
    "type": [
      {
        "en": "dragon",
        "de": "Drache"
      },
      {
        "en": "fighting",
        "de": "Kampf"
      }
    ]
  },
  {
    "id": 785,
    "name": "tapu-koko",
    "names": {
      "en": "tapu-koko",
      "de": "Kapu-Riki"
    },
    "generation_id": 7,
    "capture_rate": 3,
    "color": {
      "en": "yellow",
      "de": "Gelb"
    },
    "height": 18,
    "weight": 205,
    "cries": {
      "latest": "https:\/\/raw.githubusercontent.com\/PokeAPI\/cries\/main\/cries\/pokemon\/latest\/785.ogg",
      "legacy": null
    },
    "abilities": {
      "en": "Telepathie",
      "de": "Elektro-Erzeuger"
    },
    "type": [
      {
        "en": "electric",
        "de": "Elektro"
      },
      {
        "en": "fairy",
        "de": "Fee"
      }
    ]
  },
  {
    "id": 786,
    "name": "tapu-lele",
    "names": {
      "en": "tapu-lele",
      "de": "Kapu-Fala"
    },
    "generation_id": 7,
    "capture_rate": 3,
    "color": {
      "en": "pink",
      "de": "Rosa"
    },
    "height": 12,
    "weight": 186,
    "cries": {
      "latest": "https:\/\/raw.githubusercontent.com\/PokeAPI\/cries\/main\/cries\/pokemon\/latest\/786.ogg",
      "legacy": null
    },
    "abilities": {
      "en": "Telepathie",
      "de": "Psycho-Erzeuger"
    },
    "type": [
      {
        "en": "psychic",
        "de": "Psycho"
      },
      {
        "en": "fairy",
        "de": "Fee"
      }
    ]
  },
  {
    "id": 787,
    "name": "tapu-bulu",
    "names": {
      "en": "tapu-bulu",
      "de": "Kapu-Toro"
    },
    "generation_id": 7,
    "capture_rate": 3,
    "color": {
      "en": "red",
      "de": "Rot"
    },
    "height": 19,
    "weight": 455,
    "cries": {
      "latest": "https:\/\/raw.githubusercontent.com\/PokeAPI\/cries\/main\/cries\/pokemon\/latest\/787.ogg",
      "legacy": null
    },
    "abilities": {
      "en": "Telepathie",
      "de": "Gras-Erzeuger"
    },
    "type": [
      {
        "en": "grass",
        "de": "Pflanze"
      },
      {
        "en": "fairy",
        "de": "Fee"
      }
    ]
  },
  {
    "id": 788,
    "name": "tapu-fini",
    "names": {
      "en": "tapu-fini",
      "de": "Kapu-Kime"
    },
    "generation_id": 7,
    "capture_rate": 3,
    "color": {
      "en": "purple",
      "de": "Violett"
    },
    "height": 13,
    "weight": 212,
    "cries": {
      "latest": "https:\/\/raw.githubusercontent.com\/PokeAPI\/cries\/main\/cries\/pokemon\/latest\/788.ogg",
      "legacy": null
    },
    "abilities": {
      "en": "Telepathie",
      "de": "Nebel-Erzeuger"
    },
    "type": [
      {
        "en": "water",
        "de": "Wasser"
      },
      {
        "en": "fairy",
        "de": "Fee"
      }
    ]
  },
  {
    "id": 789,
    "name": "cosmog",
    "names": {
      "en": "cosmog",
      "de": "Cosmog"
    },
    "generation_id": 7,
    "capture_rate": 45,
    "color": {
      "en": "blue",
      "de": "Blau"
    },
    "height": 2,
    "weight": 1,
    "cries": {
      "latest": "https:\/\/raw.githubusercontent.com\/PokeAPI\/cries\/main\/cries\/pokemon\/latest\/789.ogg",
      "legacy": null
    },
    "abilities": {
      "en": null,
      "de": "Unkenntnis"
    },
    "type": [
      {
        "en": "psychic",
        "de": "Psycho"
      }
    ]
  },
  {
    "id": 790,
    "name": "cosmoem",
    "names": {
      "en": "cosmoem",
      "de": "Cosmovum"
    },
    "generation_id": 7,
    "capture_rate": 45,
    "color": {
      "en": "blue",
      "de": "Blau"
    },
    "height": 1,
    "weight": 9999,
    "cries": {
      "latest": "https:\/\/raw.githubusercontent.com\/PokeAPI\/cries\/main\/cries\/pokemon\/latest\/790.ogg",
      "legacy": null
    },
    "abilities": {
      "en": null,
      "de": "Robustheit"
    },
    "type": [
      {
        "en": "psychic",
        "de": "Psycho"
      }
    ]
  },
  {
    "id": 791,
    "name": "solgaleo",
    "names": {
      "en": "solgaleo",
      "de": "Solgaleo"
    },
    "generation_id": 7,
    "capture_rate": 45,
    "color": {
      "en": "white",
      "de": "Wei\u00df"
    },
    "height": 34,
    "weight": 2300,
    "cries": {
      "latest": "https:\/\/raw.githubusercontent.com\/PokeAPI\/cries\/main\/cries\/pokemon\/latest\/791.ogg",
      "legacy": null
    },
    "abilities": {
      "en": null,
      "de": "Metallprotektor"
    },
    "type": [
      {
        "en": "psychic",
        "de": "Psycho"
      },
      {
        "en": "steel",
        "de": "Stahl"
      }
    ]
  },
  {
    "id": 792,
    "name": "lunala",
    "names": {
      "en": "lunala",
      "de": "Lunala"
    },
    "generation_id": 7,
    "capture_rate": 45,
    "color": {
      "en": "purple",
      "de": "Violett"
    },
    "height": 40,
    "weight": 1200,
    "cries": {
      "latest": "https:\/\/raw.githubusercontent.com\/PokeAPI\/cries\/main\/cries\/pokemon\/latest\/792.ogg",
      "legacy": null
    },
    "abilities": {
      "en": null,
      "de": "Phantomschutz"
    },
    "type": [
      {
        "en": "psychic",
        "de": "Psycho"
      },
      {
        "en": "ghost",
        "de": "Geist"
      }
    ]
  },
  {
    "id": 793,
    "name": "nihilego",
    "names": {
      "en": "nihilego",
      "de": "Anego"
    },
    "generation_id": 7,
    "capture_rate": 45,
    "color": {
      "en": "white",
      "de": "Wei\u00df"
    },
    "height": 12,
    "weight": 555,
    "cries": {
      "latest": "https:\/\/raw.githubusercontent.com\/PokeAPI\/cries\/main\/cries\/pokemon\/latest\/793.ogg",
      "legacy": null
    },
    "abilities": {
      "en": null,
      "de": "Bestien-Boost"
    },
    "type": [
      {
        "en": "rock",
        "de": "Gestein"
      },
      {
        "en": "poison",
        "de": "Gift"
      }
    ]
  },
  {
    "id": 794,
    "name": "buzzwole",
    "names": {
      "en": "buzzwole",
      "de": "Masskito"
    },
    "generation_id": 7,
    "capture_rate": 45,
    "color": {
      "en": "red",
      "de": "Rot"
    },
    "height": 24,
    "weight": 3336,
    "cries": {
      "latest": "https:\/\/raw.githubusercontent.com\/PokeAPI\/cries\/main\/cries\/pokemon\/latest\/794.ogg",
      "legacy": null
    },
    "abilities": {
      "en": null,
      "de": "Bestien-Boost"
    },
    "type": [
      {
        "en": "bug",
        "de": "K\u00e4fer"
      },
      {
        "en": "fighting",
        "de": "Kampf"
      }
    ]
  },
  {
    "id": 795,
    "name": "pheromosa",
    "names": {
      "en": "pheromosa",
      "de": "Schabelle"
    },
    "generation_id": 7,
    "capture_rate": 45,
    "color": {
      "en": "white",
      "de": "Wei\u00df"
    },
    "height": 18,
    "weight": 250,
    "cries": {
      "latest": "https:\/\/raw.githubusercontent.com\/PokeAPI\/cries\/main\/cries\/pokemon\/latest\/795.ogg",
      "legacy": null
    },
    "abilities": {
      "en": null,
      "de": "Bestien-Boost"
    },
    "type": [
      {
        "en": "bug",
        "de": "K\u00e4fer"
      },
      {
        "en": "fighting",
        "de": "Kampf"
      }
    ]
  },
  {
    "id": 796,
    "name": "xurkitree",
    "names": {
      "en": "xurkitree",
      "de": "Voltriant"
    },
    "generation_id": 7,
    "capture_rate": 45,
    "color": {
      "en": "black",
      "de": "Schwarz"
    },
    "height": 38,
    "weight": 1000,
    "cries": {
      "latest": "https:\/\/raw.githubusercontent.com\/PokeAPI\/cries\/main\/cries\/pokemon\/latest\/796.ogg",
      "legacy": null
    },
    "abilities": {
      "en": null,
      "de": "Bestien-Boost"
    },
    "type": [
      {
        "en": "electric",
        "de": "Elektro"
      }
    ]
  },
  {
    "id": 797,
    "name": "celesteela",
    "names": {
      "en": "celesteela",
      "de": "Kaguron"
    },
    "generation_id": 7,
    "capture_rate": 45,
    "color": {
      "en": "green",
      "de": "Gr\u00fcn"
    },
    "height": 92,
    "weight": 9999,
    "cries": {
      "latest": "https:\/\/raw.githubusercontent.com\/PokeAPI\/cries\/main\/cries\/pokemon\/latest\/797.ogg",
      "legacy": null
    },
    "abilities": {
      "en": null,
      "de": "Bestien-Boost"
    },
    "type": [
      {
        "en": "steel",
        "de": "Stahl"
      },
      {
        "en": "flying",
        "de": "Flug"
      }
    ]
  },
  {
    "id": 798,
    "name": "kartana",
    "names": {
      "en": "kartana",
      "de": "Katagami"
    },
    "generation_id": 7,
    "capture_rate": 45,
    "color": {
      "en": "white",
      "de": "Wei\u00df"
    },
    "height": 3,
    "weight": 1,
    "cries": {
      "latest": "https:\/\/raw.githubusercontent.com\/PokeAPI\/cries\/main\/cries\/pokemon\/latest\/798.ogg",
      "legacy": null
    },
    "abilities": {
      "en": null,
      "de": "Bestien-Boost"
    },
    "type": [
      {
        "en": "grass",
        "de": "Pflanze"
      },
      {
        "en": "steel",
        "de": "Stahl"
      }
    ]
  },
  {
    "id": 799,
    "name": "guzzlord",
    "names": {
      "en": "guzzlord",
      "de": "Schlingking"
    },
    "generation_id": 7,
    "capture_rate": 45,
    "color": {
      "en": "black",
      "de": "Schwarz"
    },
    "height": 55,
    "weight": 8880,
    "cries": {
      "latest": "https:\/\/raw.githubusercontent.com\/PokeAPI\/cries\/main\/cries\/pokemon\/latest\/799.ogg",
      "legacy": null
    },
    "abilities": {
      "en": null,
      "de": "Bestien-Boost"
    },
    "type": [
      {
        "en": "dark",
        "de": "Unlicht"
      },
      {
        "en": "dragon",
        "de": "Drache"
      }
    ]
  },
  {
    "id": 800,
    "name": "necrozma",
    "names": {
      "en": "necrozma",
      "de": "Necrozma"
    },
    "generation_id": 7,
    "capture_rate": 255,
    "color": {
      "en": "black",
      "de": "Schwarz"
    },
    "height": 24,
    "weight": 2300,
    "cries": {
      "latest": "https:\/\/raw.githubusercontent.com\/PokeAPI\/cries\/main\/cries\/pokemon\/latest\/800.ogg",
      "legacy": null
    },
    "abilities": {
      "en": null,
      "de": "Prismar\u00fcstung"
    },
    "type": [
      {
        "en": "psychic",
        "de": "Psycho"
      }
    ]
  },
  {
    "id": 801,
    "name": "magearna",
    "names": {
      "en": "magearna",
      "de": "Magearna"
    },
    "generation_id": 7,
    "capture_rate": 3,
    "color": {
      "en": "gray",
      "de": "Grau"
    },
    "height": 10,
    "weight": 805,
    "cries": {
      "latest": "https:\/\/raw.githubusercontent.com\/PokeAPI\/cries\/main\/cries\/pokemon\/latest\/801.ogg",
      "legacy": null
    },
    "abilities": {
      "en": null,
      "de": "Seelenherz"
    },
    "type": [
      {
        "en": "steel",
        "de": "Stahl"
      },
      {
        "en": "fairy",
        "de": "Fee"
      }
    ]
  },
  {
    "id": 802,
    "name": "marshadow",
    "names": {
      "en": "marshadow",
      "de": "Marshadow"
    },
    "generation_id": 7,
    "capture_rate": 3,
    "color": {
      "en": "gray",
      "de": "Grau"
    },
    "height": 7,
    "weight": 222,
    "cries": {
      "latest": "https:\/\/raw.githubusercontent.com\/PokeAPI\/cries\/main\/cries\/pokemon\/latest\/802.ogg",
      "legacy": null
    },
    "abilities": {
      "en": null,
      "de": "Techniker"
    },
    "type": [
      {
        "en": "fighting",
        "de": "Kampf"
      },
      {
        "en": "ghost",
        "de": "Geist"
      }
    ]
  },
  {
    "id": 803,
    "name": "poipole",
    "names": {
      "en": "poipole",
      "de": "Venicro"
    },
    "generation_id": 7,
    "capture_rate": 45,
    "color": {
      "en": "purple",
      "de": "Violett"
    },
    "height": 6,
    "weight": 18,
    "cries": {
      "latest": "https:\/\/raw.githubusercontent.com\/PokeAPI\/cries\/main\/cries\/pokemon\/latest\/803.ogg",
      "legacy": null
    },
    "abilities": {
      "en": null,
      "de": "Bestien-Boost"
    },
    "type": [
      {
        "en": "poison",
        "de": "Gift"
      }
    ]
  },
  {
    "id": 804,
    "name": "naganadel",
    "names": {
      "en": "naganadel",
      "de": "Agoyon"
    },
    "generation_id": 7,
    "capture_rate": 45,
    "color": {
      "en": "purple",
      "de": "Violett"
    },
    "height": 36,
    "weight": 1500,
    "cries": {
      "latest": "https:\/\/raw.githubusercontent.com\/PokeAPI\/cries\/main\/cries\/pokemon\/latest\/804.ogg",
      "legacy": null
    },
    "abilities": {
      "en": null,
      "de": "Bestien-Boost"
    },
    "type": [
      {
        "en": "poison",
        "de": "Gift"
      },
      {
        "en": "dragon",
        "de": "Drache"
      }
    ]
  },
  {
    "id": 805,
    "name": "stakataka",
    "names": {
      "en": "stakataka",
      "de": "Muramura"
    },
    "generation_id": 7,
    "capture_rate": 30,
    "color": {
      "en": "gray",
      "de": "Grau"
    },
    "height": 55,
    "weight": 8200,
    "cries": {
      "latest": "https:\/\/raw.githubusercontent.com\/PokeAPI\/cries\/main\/cries\/pokemon\/latest\/805.ogg",
      "legacy": null
    },
    "abilities": {
      "en": null,
      "de": "Bestien-Boost"
    },
    "type": [
      {
        "en": "rock",
        "de": "Gestein"
      },
      {
        "en": "steel",
        "de": "Stahl"
      }
    ]
  },
  {
    "id": 806,
    "name": "blacephalon",
    "names": {
      "en": "blacephalon",
      "de": "Kopplosio"
    },
    "generation_id": 7,
    "capture_rate": 30,
    "color": {
      "en": "white",
      "de": "Wei\u00df"
    },
    "height": 18,
    "weight": 130,
    "cries": {
      "latest": "https:\/\/raw.githubusercontent.com\/PokeAPI\/cries\/main\/cries\/pokemon\/latest\/806.ogg",
      "legacy": null
    },
    "abilities": {
      "en": null,
      "de": "Bestien-Boost"
    },
    "type": [
      {
        "en": "fire",
        "de": "Feuer"
      },
      {
        "en": "ghost",
        "de": "Geist"
      }
    ]
  },
  {
    "id": 807,
    "name": "zeraora",
    "names": {
      "en": "zeraora",
      "de": "Zeraora"
    },
    "generation_id": 7,
    "capture_rate": 3,
    "color": {
      "en": "yellow",
      "de": "Gelb"
    },
    "height": 15,
    "weight": 445,
    "cries": {
      "latest": "https:\/\/raw.githubusercontent.com\/PokeAPI\/cries\/main\/cries\/pokemon\/latest\/807.ogg",
      "legacy": null
    },
    "abilities": {
      "en": null,
      "de": "Voltabsorber"
    },
    "type": [
      {
        "en": "electric",
        "de": "Elektro"
      }
    ]
  },
  {
    "id": 808,
    "name": "meltan",
    "names": {
      "en": "meltan",
      "de": "Meltan"
    },
    "generation_id": 7,
    "capture_rate": 3,
    "color": {
      "en": "gray",
      "de": "Grau"
    },
    "height": 2,
    "weight": 80,
    "cries": {
      "latest": "https:\/\/raw.githubusercontent.com\/PokeAPI\/cries\/main\/cries\/pokemon\/latest\/808.ogg",
      "legacy": null
    },
    "abilities": {
      "en": null,
      "de": "Magnetfalle"
    },
    "type": [
      {
        "en": "steel",
        "de": "Stahl"
      }
    ]
  },
  {
    "id": 809,
    "name": "melmetal",
    "names": {
      "en": "melmetal",
      "de": "Melmetal"
    },
    "generation_id": 7,
    "capture_rate": 3,
    "color": {
      "en": "gray",
      "de": "Grau"
    },
    "height": 25,
    "weight": 8000,
    "cries": {
      "latest": "https:\/\/raw.githubusercontent.com\/PokeAPI\/cries\/main\/cries\/pokemon\/latest\/809.ogg",
      "legacy": null
    },
    "abilities": {
      "en": null,
      "de": "Eisenfaust"
    },
    "type": [
      {
        "en": "steel",
        "de": "Stahl"
      }
    ]
  }
]
